voidring/__init__.py
voidring/__version__.py
voidring/base_rocksdb.py
voidring/cache/__init__.py
voidring/cache/cache_rocksdb.py
voidring/index/__init__.py
voidring/index/accessor.py
voidring/index/index_rocksdb.py
voidring/index/path_parser.py
voidring-0.1.3.dist-info/METADATA
voidring-0.1.3.dist-info/WHEEL
voidring-0.1.3.dist-info/RECORD
